{
  "portraitScale": 1.0,
  "portraitTranslation": [0.0, 0.0, 0],
  "profileScale": 0.85,
  "profileTranslation": [0.0, 0.0, 0],
  "rootBone": "gmax_drednaw",
  "poses": {
    "standing": {
      "poseName": "standing",
      "poseTypes": ["STAND", "NONE", "PORTRAIT", "PROFILE", "FLOAT"],
      "animations": ["q.bedrock('gmaxdrednaw', 'ground_idle')"]
    },
    "walking": {
      "poseName": "walking",
      "poseTypes": ["WALK", "SWIM"],
      "animations": ["q.bedrock('gmaxdrednaw', 'ground_walk')"]
    }
  }
}
